truth/__init__.py
truth/convert.py
truth/convert_test.py
truth/truth.py
truth/truth_test.py
pytruth-1.1.0.dist-info/LICENSE
pytruth-1.1.0.dist-info/METADATA
pytruth-1.1.0.dist-info/WHEEL
pytruth-1.1.0.dist-info/top_level.txt
pytruth-1.1.0.dist-info/RECORD
