Metadata-Version: 2.1
Name: pytruth
Version: 1.1.0
Summary: Provides unittest assertions in a fluent style.
Home-page: https://github.com/google/pytruth
Author: Gregory Kwok
Author-email: gkwok@google.com
License: Apache 2.0
Project-URL: Source, https://github.com/google/pytruth
Project-URL: Bug Reports, https://groups.google.com/d/forum/pytruth-users
Platform: UNKNOWN
Classifier: Development Status :: 5 - Production/Stable
Classifier: Intended Audience :: Developers
Classifier: License :: OSI Approved :: Apache Software License
Classifier: Operating System :: OS Independent
Classifier: Programming Language :: Python
Classifier: Programming Language :: Python :: 2
Classifier: Programming Language :: Python :: 2.7
Classifier: Programming Language :: Python :: 3
Classifier: Programming Language :: Python :: 3.4
Classifier: Programming Language :: Python :: 3.5
Classifier: Programming Language :: Python :: 3.6
Classifier: Programming Language :: Python :: 3.7
Classifier: Topic :: Software Development :: Libraries :: Python Modules
Classifier: Topic :: Software Development :: Quality Assurance
Classifier: Topic :: Software Development :: Testing
Classifier: Topic :: Software Development :: Testing :: Mocking
Classifier: Topic :: Software Development :: Testing :: Unit
Requires-Dist: six
Requires-Dist: wheel
